cdk_aspect_vpc_stateful_cidr_block_assigner/__init__.py
cdk_aspect_vpc_stateful_cidr_block_assigner/py.typed
cdk_aspect_vpc_stateful_cidr_block_assigner/_jsii/__init__.py
cdk_aspect_vpc_stateful_cidr_block_assigner/_jsii/cdk-aspect-vpc-stateful-cidr-block-assigner@0.0.9.jsii.tgz
cdk_aspect_vpc_stateful_cidr_block_assigner-0.0.9.dist-info/LICENSE
cdk_aspect_vpc_stateful_cidr_block_assigner-0.0.9.dist-info/METADATA
cdk_aspect_vpc_stateful_cidr_block_assigner-0.0.9.dist-info/WHEEL
cdk_aspect_vpc_stateful_cidr_block_assigner-0.0.9.dist-info/top_level.txt
cdk_aspect_vpc_stateful_cidr_block_assigner-0.0.9.dist-info/RECORD
