Metadata-Version: 2.1
Name: cdk-aspect-vpc-stateful-cidr-block-assigner
Version: 0.0.9
Summary: CDK Aspect to alter the Amazon VPC subnet CIDR blocks assignment to respect existing CIDR blocks when updating a CDK Vpc construct
Home-page: https://github.com/fibert/cdk-aspect-vpc-stateful-cidr-block-assigner.git
Author: Dor Fibert<dorfib@gmail.com>
License: Apache-2.0
Project-URL: Source, https://github.com/fibert/cdk-aspect-vpc-stateful-cidr-block-assigner.git
Classifier: Intended Audience :: Developers
Classifier: Operating System :: OS Independent
Classifier: Programming Language :: JavaScript
Classifier: Programming Language :: Python :: 3 :: Only
Classifier: Programming Language :: Python :: 3.9
Classifier: Programming Language :: Python :: 3.10
Classifier: Programming Language :: Python :: 3.11
Classifier: Typing :: Typed
Classifier: Development Status :: 5 - Production/Stable
Classifier: License :: OSI Approved
Requires-Python: ~=3.9
License-File: LICENSE
Requires-Dist: aws-cdk-lib<3.0.0,>=2.178.1
Requires-Dist: constructs<11.0.0,>=10.0.5
Requires-Dist: jsii<2.0.0,>=1.109.0
Requires-Dist: publication>=0.0.3
Requires-Dist: typeguard<4.3.0,>=2.13.3
